neon_stt_plugin_nemo_remote/__init__.py
neon_stt_plugin_nemo_remote-0.0.1a6.dist-info/LICENSE.md
neon_stt_plugin_nemo_remote-0.0.1a6.dist-info/METADATA
neon_stt_plugin_nemo_remote-0.0.1a6.dist-info/WHEEL
neon_stt_plugin_nemo_remote-0.0.1a6.dist-info/entry_points.txt
neon_stt_plugin_nemo_remote-0.0.1a6.dist-info/top_level.txt
neon_stt_plugin_nemo_remote-0.0.1a6.dist-info/zip-safe
neon_stt_plugin_nemo_remote-0.0.1a6.dist-info/RECORD
