Metadata-Version: 2.1
Name: neon-stt-plugin-nemo-remote
Version: 0.0.1a6
Summary: Nemo Remote STT plugin for Neon
Home-page: https://github.com/NeonGeckoCom/neon-stt-plugin-nemo-remote
Author: Neongecko
Author-email: developers@neon.ai
License: BSD-3.0
Keywords: mycroft plugin stt
Classifier: Intended Audience :: Developers
Classifier: Topic :: Text Processing :: Linguistic
Classifier: Programming Language :: Python :: 3.8
License-File: LICENSE.md
Requires-Dist: ovos-plugin-manager>=0.0.24,~=0.0
Requires-Dist: ovos-utils>=0.0.30,~=0.0
Requires-Dist: SpeechRecognition~=3.8
